{
   "test_production_file":false,
   "title":"La fuga de Cleopatra",
   "imageBackground":"./assets/images/demo_egipto/egipto_fondo.jpg",
   "opacityBackground":".3",
   "M":2,
   "N":3,
   "Mextra":0,
   "Nextra":0,
   "time":"50",
   "heightImg":"",
   "widthImg":"",
   "numberAttempts":"-1",
   "numberClues":"35",
   "clues":false,
   "cluesTime":"8000",
   "initialMessage":"Bienvenido al Generador de Puzzles. ",
   "initialMessagePrint":"¡Ánimo!",
   "initialImage":"./assets/images/cascada.jpg",
   "endMessageSuccess":"Enhorabuena has finalizado el puzzle.",
   "endMessageFail":"Esa no es la solución.",
   "endImageSuccess":"./assets/images/taj_mahal.jpg",
   "endImageFail":"./assets/images/noruega.jpg",
   "solution":"b9ab36d0bd4e20b61eb0566846f40578",
   "debug":true,
   "debug_scorm_api":false,
   "debug_scorm_api_window":false,
   "available_locales":[
      "es",
      "en"
   ],
   "adaptive":true,
   "finish_screen":true,
   "scorm":{
      "completion_threshold":0.5,
      "score_threshold":0.6
   },
   "images":[
      {
         "id":"15135",
         "path":"./assets/images/crop/15135.jpg"
      },
      {
         "id":"41105",
         "path":"./assets/images/crop/41105.jpg"
      },
      {
         "id":"20966",
         "path":"./assets/images/crop/20966.jpg"
      },
      {
         "id":"6298",
         "path":"./assets/images/crop/6298.jpg"
      },
      {
         "id":"50239",
         "path":"./assets/images/crop/50239.jpg"
      },
      {
         "id":"27742",
         "path":"./assets/images/crop/27742.jpg"
      },
      {
         "id":"71412",
         "path":"./assets/images/crop/71412.jpg"
      },
      {
         "id":"76366",
         "path":"./assets/images/crop/76366.jpg"
      },
      {
         "id":"38335",
         "path":"./assets/images/crop/38335.jpg"
      },
      {
         "id":"79294",
         "path":"./assets/images/crop/79294.jpg"
      },
      {
         "id":"50306",
         "path":"./assets/images/crop/50306.jpg"
      },
      {
         "id":"81625",
         "path":"./assets/images/crop/81625.jpg"
      },
      {
         "id":"61987",
         "path":"./assets/images/crop/61987.jpg"
      },
      {
         "id":"47086",
         "path":"./assets/images/crop/47086.jpg"
      },
      {
         "id":"55152",
         "path":"./assets/images/crop/55152.jpg"
      },
      {
         "id":"25445",
         "path":"./assets/images/crop/25445.jpg"
      },
      {
         "id":"96661",
         "path":"./assets/images/crop/96661.jpg"
      },
      {
         "id":"61292",
         "path":"./assets/images/crop/61292.jpg"
      },
      {
         "id":"45492",
         "path":"./assets/images/crop/45492.jpg"
      },
      {
         "id":"85261",
         "path":"./assets/images/crop/85261.jpg"
      },
      {
         "id":"64380",
         "path":"./assets/images/crop/64380.jpg"
      },
      {
         "id":"64647",
         "path":"./assets/images/crop/64647.jpg"
      },
      {
         "id":"39015",
         "path":"./assets/images/crop/39015.jpg"
      },
      {
         "id":"18709",
         "path":"./assets/images/crop/18709.jpg"
      }
   ]
}